{
  "All items on Website": "6870",
  "Correct currency": {
    "$": 3182,
    "\u20ac": 3688
  },
  "Items colour": {
    "Argent": 1,
    "BAROCCO": 2,
    "BRIGHT CRYSTAL": 1,
    "Barocco": 36,
    "Beige": 2,
    "Black": 66,
    "Black /red": 1,
    "Black/Gold": 14,
    "Black/Green": 1,
    "Black/White": 2,
    "Blanc": 13,
    "Blanc/Noir/Or": 10,
    "Blanc/Or": 13,
    "Bleu": 10,
    "Bleu Royale": 3,
    "Blue": 19,
    "Bluette": 2,
    "Brun": 2,
    "Burgundy": 11,
    "DYLAN BLUE": 3,
    "Dylan Blue": 3,
    "Fuchsia Pink": 9,
    "Fuchsia Pink /Black": 1,
    "Glass and Cristal": 20,
    "Gold": 25,
    "Gray": 4,
    "Gray/Gold/Blue": 3,
    "Green": 1,
    "Green/Black": 6,
    "Gris/Or": 2,
    "Gris/Or /Bleu": 2,
    "Havana": 2,
    "I \u2661 Baroque": 7,
    "Imprimer": 16,
    "Jaune": 17,
    "LE JARDINDISH": 1,
    "Le Grand Divertissement": 16,
    "Le Jardin de Versace": 2,
    "Les Tr\u00e9sors de la Mer": 2,
    "Light Blue": 5,
    "Medusa Lumiere": 10,
    "Medusa Red": 1,
    "N1194": 2,
    "N1428": 2,
    "N1429": 2,
    "N1440": 9,
    "N1446": 5,
    "N1448": 3,
    "N1449": 3,
    "N1933": 37,
    "N2066": 8,
    "N6905": 4,
    "N6908": 2,
    "N6912": 7,
    "Noir": 52,
    "Noir/Blanc": 6,
    "Noir/Or": 8,
    "ONUL": 86,
    "Or": 23,
    "Orange": 5,
    "Orange/Champagne": 1,
    "Orange/Print": 1,
    "PNUL": 23,
    "Pink": 2,
    "Prestige Gala": 6,
    "Prestige Gala Le Blue": 1,
    "Print": 26,
    "RNUL": 3,
    "Red": 21,
    "Red Medusa": 15,
    "Rose": 2,
    "Rouge": 10,
    "Silver": 3,
    "Treasury": 2,
    "WINTER'S NIGHT": 1,
    "WNUL": 4,
    "White": 29,
    "White/Black/Gold": 6,
    "White/Gold": 2,
    "Yellow": 14,
    "Z7604": 4,
    "animalier": 40,
    "argent": 19,
    "argent+or": 1,
    "beige": 2,
    "beu": 1,
    "black": 978,
    "black+gold": 17,
    "black+gray": 1,
    "black+print": 7,
    "black+white": 8,
    "blanc": 365,
    "blanc + noir": 5,
    "blanc+bleu": 2,
    "blanc+imprimer": 11,
    "blanc+noir": 12,
    "bleu": 240,
    "bleu clair": 4,
    "bleu+gris": 1,
    "bleu+or": 2,
    "bleu+rose": 1,
    "bleu+rouge": 3,
    "blue": 186,
    "blue+pink": 2,
    "blue+red": 2,
    "bluette": 4,
    "brown": 17,
    "brun": 23,
    "brun+or": 4,
    "fluo orange": 2,
    "fluo pink": 4,
    "fluo yellow": 3,
    "fuchsia": 8,
    "fuchsia/noir": 1,
    "gold": 199,
    "gold+silver": 12,
    "gray": 23,
    "gray+print": 2,
    "green": 50,
    "green+gold": 3,
    "gris": 24,
    "gris+imprimer": 3,
    "havana": 5,
    "imprimer": 783,
    "imprimer+m\u00e9tallique": 1,
    "imprimer+or": 1,
    "imprim\u00e9": 3,
    "jaune": 25,
    "jaune fluo": 2,
    "jaune+or": 4,
    "m\u00e9tallique": 2,
    "neutrals": 7,
    "neutres": 11,
    "noir": 1030,
    "noir rouge": 3,
    "noir+blanc": 6,
    "noir+imprimer": 9,
    "noir+or": 20,
    "noir+rose": 3,
    "noir/or": 7,
    "or": 258,
    "or+argent": 17,
    "orange": 37,
    "orange fluo": 2,
    "orange/champagne": 2,
    "orange/imprim\u00e9": 1,
    "pink": 123,
    "pink+burgundy": 2,
    "pink+gold": 5,
    "pink+print": 2,
    "print": 663,
    "red": 65,
    "red+black": 2,
    "red+gold": 9,
    "rose": 133,
    "rose fluo": 2,
    "rose+bleu": 1,
    "rose+bordeaux": 2,
    "rose+imprimer": 6,
    "rose+noir": 2,
    "rose+or": 5,
    "rouge": 74,
    "rouge+noir": 2,
    "rouge+or": 7,
    "silver": 12,
    "vert": 42,
    "vert fluo": 2,
    "vert+or": 4,
    "vert/noir": 4,
    "violet": 23,
    "white": 282,
    "white + black": 6,
    "white + gold": 1,
    "white+black": 13,
    "white+blue": 2,
    "white+gold": 1,
    "white+print": 11,
    "white/gold": 7,
    "yellow": 14,
    "yellow+gold": 3
  },
  "Items region": {
    "France": 3688,
    "United States": 3182
  },
  "Items size": {
    "0-3M": 2,
    "1": 4,
    "10": 2,
    "100": 28,
    "105": 18,
    "10A": 6,
    "11": 10,
    "110": 16,
    "115": 11,
    "120": 4,
    "125": 3,
    "12A": 4,
    "12M18": 13,
    "13": 16,
    "14A": 3,
    "15": 20,
    "16": 1,
    "17": 22,
    "18": 1,
    "18M24": 9,
    "19": 22,
    "1B": 2,
    "1C": 4,
    "1D": 1,
    "2": 4,
    "20": 1,
    "21": 19,
    "22": 3,
    "23": 20,
    "24": 8,
    "24M": 10,
    "25": 28,
    "25-26": 1,
    "25-27": 1,
    "26": 20,
    "27": 26,
    "27-28": 1,
    "28": 19,
    "28-30": 1,
    "29": 27,
    "29-30": 2,
    "2B": 2,
    "2C": 3,
    "2XL": 17,
    "3": 8,
    "3-6M": 11,
    "30": 39,
    "31": 27,
    "31-32": 2,
    "31-33": 1,
    "32": 32,
    "33": 24,
    "33-34": 2,
    "34": 29,
    "34-37": 1,
    "35": 18,
    "35.5": 5,
    "36": 65,
    "36.5": 11,
    "36M": 9,
    "37": 44,
    "37.5": 20,
    "38": 91,
    "38-40": 1,
    "38.5": 16,
    "39": 88,
    "39.5": 33,
    "3B": 2,
    "3C": 3,
    "3XL": 16,
    "4": 10,
    "40": 126,
    "40.5": 32,
    "41": 88,
    "41.5": 37,
    "42": 92,
    "42.5": 41,
    "43": 70,
    "43.5": 40,
    "44": 84,
    "44.5": 33,
    "45": 61,
    "45.5": 17,
    "46": 79,
    "46.5": 8,
    "47": 31,
    "47.5": 9,
    "48": 32,
    "4A": 4,
    "4B": 2,
    "4C": 2,
    "4XL": 13,
    "5": 8,
    "50": 23,
    "52": 20,
    "54": 15,
    "55": 2,
    "56": 10,
    "57": 2,
    "58": 8,
    "59": 2,
    "5A": 4,
    "5B": 1,
    "5XL": 8,
    "6": 4,
    "6 1/2": 1,
    "6-9M": 14,
    "60": 9,
    "65": 9,
    "6A": 6,
    "6XL": 4,
    "7": 10,
    "7 1/2": 1,
    "70": 16,
    "75": 22,
    "8": 7,
    "8 1/2": 2,
    "80": 30,
    "85": 32,
    "8A": 6,
    "9": 9,
    "9 1/2": 2,
    "9-12M": 12,
    "90": 31,
    "95": 31,
    "CALKI": 1,
    "KING": 2,
    "L": 32,
    "L-54": 2,
    "L/XL": 1,
    "M": 35,
    "M-46": 1,
    "M-52": 2,
    "QUEEN": 1,
    "S": 31,
    "S-42": 1,
    "S-50": 2,
    "S/M": 1,
    "XL": 30,
    "XL-56": 1,
    "XS": 19,
    "XXL": 7,
    "XXS": 2,
    "XXXL": 4,
    "no available": 1
  }
}